{
  "Projapati 2 [2D | Bengali]": {
    "shows": 44,
    "gross": 236870.0,
    "sold": 1806,
    "totalSeats": 10603,
    "venues": 21,
    "cities": 9,
    "fastfilling": 6,
    "housefull": 1,
    "occupancy": 17.03
  },
  "Dhurandhar [2D | Hindi]": {
    "shows": 887,
    "gross": 8689989.0,
    "sold": 32533,
    "totalSeats": 183116,
    "venues": 224,
    "cities": 73,
    "fastfilling": 110,
    "housefull": 0,
    "occupancy": 17.77
  },
  "Mitin: Ekti Khunir Sandhaney [2D | Bengali]": {
    "shows": 8,
    "gross": 18450.0,
    "sold": 151,
    "totalSeats": 1626,
    "venues": 8,
    "cities": 5,
    "fastfilling": 0,
    "housefull": 0,
    "occupancy": 9.29
  },
  "Avatar: Fire and Ash [2D | Hindi]": {
    "shows": 34,
    "gross": 55845.0,
    "sold": 316,
    "totalSeats": 6842,
    "venues": 24,
    "cities": 18,
    "fastfilling": 0,
    "housefull": 0,
    "occupancy": 4.62
  },
  "Tu Meri Main Tera Main Tera Tu Meri [2D | Hindi]": {
    "shows": 345,
    "gross": 1071675.0,
    "sold": 4567,
    "totalSeats": 58691,
    "venues": 163,
    "cities": 52,
    "fastfilling": 2,
    "housefull": 2,
    "occupancy": 7.78
  },
  "Tere Ishk Mein [2D | Hindi]": {
    "shows": 9,
    "gross": 42910.0,
    "sold": 177,
    "totalSeats": 1549,
    "venues": 6,
    "cities": 4,
    "fastfilling": 1,
    "housefull": 0,
    "occupancy": 11.43
  },
  "Champion [2D | Telugu]": {
    "shows": 58,
    "gross": 296048.0,
    "sold": 1933,
    "totalSeats": 20434,
    "venues": 38,
    "cities": 16,
    "fastfilling": 4,
    "housefull": 0,
    "occupancy": 9.46
  },
  "Avatar: Fire and Ash [3D | Telugu]": {
    "shows": 20,
    "gross": 105977.0,
    "sold": 722,
    "totalSeats": 5562,
    "venues": 8,
    "cities": 8,
    "fastfilling": 0,
    "housefull": 0,
    "occupancy": 12.98
  },
  "Aghosham [2D | Malayalam]": {
    "shows": 14,
    "gross": 30529.0,
    "sold": 169,
    "totalSeats": 2214,
    "venues": 12,
    "cities": 6,
    "fastfilling": 0,
    "housefull": 0,
    "occupancy": 7.63
  },
  "Sarvam Maya [2D | Malayalam]": {
    "shows": 209,
    "gross": 4212365.8,
    "sold": 21555,
    "totalSeats": 56386,
    "venues": 70,
    "cities": 26,
    "fastfilling": 92,
    "housefull": 0,
    "occupancy": 38.23
  },
  "Avatar: Fire and Ash [3D | Hindi]": {
    "shows": 179,
    "gross": 1385158.0,
    "sold": 5038,
    "totalSeats": 34534,
    "venues": 98,
    "cities": 34,
    "fastfilling": 14,
    "housefull": 0,
    "occupancy": 14.59
  },
  "Vande Bharat Via USA [2D | Gujarati]": {
    "shows": 21,
    "gross": 22480.0,
    "sold": 145,
    "totalSeats": 3159,
    "venues": 18,
    "cities": 4,
    "fastfilling": 0,
    "housefull": 0,
    "occupancy": 4.59
  },
  "Anaconda [2D | Hindi]": {
    "shows": 71,
    "gross": 114280.0,
    "sold": 663,
    "totalSeats": 13705,
    "venues": 63,
    "cities": 28,
    "fastfilling": 0,
    "housefull": 0,
    "occupancy": 4.84
  },
  "Laalo - Krishna Sada Sahaayate [2D | Gujarati]": {
    "shows": 38,
    "gross": 58894.0,
    "sold": 417,
    "totalSeats": 6393,
    "venues": 16,
    "cities": 5,
    "fastfilling": 0,
    "housefull": 0,
    "occupancy": 6.52
  },
  "Ajab Tarzan Ni Gajab Kahani [2D | Gujarati]": {
    "shows": 1,
    "gross": 0.0,
    "sold": 0,
    "totalSeats": 41,
    "venues": 1,
    "cities": 1,
    "fastfilling": 0,
    "housefull": 0,
    "occupancy": 0.0
  },
  "Shambhala [2D | Telugu]": {
    "shows": 46,
    "gross": 296580.0,
    "sold": 2100,
    "totalSeats": 15192,
    "venues": 24,
    "cities": 13,
    "fastfilling": 4,
    "housefull": 0,
    "occupancy": 13.82
  },
  "Dhanesh Ke Aradhna [2D | Chattisgarhi]": {
    "shows": 6,
    "gross": 14340.0,
    "sold": 122,
    "totalSeats": 1638,
    "venues": 2,
    "cities": 2,
    "fastfilling": 0,
    "housefull": 0,
    "occupancy": 7.45
  },
  "Asha (2025) [2D | Marathi]": {
    "shows": 6,
    "gross": 1820.0,
    "sold": 13,
    "totalSeats": 1085,
    "venues": 6,
    "cities": 6,
    "fastfilling": 0,
    "housefull": 0,
    "occupancy": 1.2
  },
  "Bha. Bha. Ba. [2D | Malayalam]": {
    "shows": 84,
    "gross": 103921.0,
    "sold": 589,
    "totalSeats": 19330,
    "venues": 43,
    "cities": 18,
    "fastfilling": 0,
    "housefull": 0,
    "occupancy": 3.05
  },
  "Avatar: Fire and Ash [3D | Tamil]": {
    "shows": 26,
    "gross": 173602.85,
    "sold": 1060,
    "totalSeats": 10942,
    "venues": 15,
    "cities": 10,
    "fastfilling": 1,
    "housefull": 0,
    "occupancy": 9.69
  },
  "Sirai [2D | Tamil]": {
    "shows": 36,
    "gross": 188448.5,
    "sold": 1211,
    "totalSeats": 8671,
    "venues": 23,
    "cities": 8,
    "fastfilling": 1,
    "housefull": 0,
    "occupancy": 13.97
  },
  "Retta Thala [2D | Tamil]": {
    "shows": 25,
    "gross": 91675.0,
    "sold": 700,
    "totalSeats": 7545,
    "venues": 17,
    "cities": 9,
    "fastfilling": 1,
    "housefull": 0,
    "occupancy": 9.28
  },
  "Akhanda 2: Thaandavam [2D | Telugu]": {
    "shows": 28,
    "gross": 181632.0,
    "sold": 1454,
    "totalSeats": 8997,
    "venues": 12,
    "cities": 10,
    "fastfilling": 2,
    "housefull": 0,
    "occupancy": 16.16
  },
  "Avatar: Fire and Ash [3D | English]": {
    "shows": 124,
    "gross": 1713870.8,
    "sold": 5583,
    "totalSeats": 24897,
    "venues": 69,
    "cities": 19,
    "fastfilling": 19,
    "housefull": 0,
    "occupancy": 22.42
  },
  "Mindiyum Paranjum [2D | Malayalam]": {
    "shows": 10,
    "gross": 19870.0,
    "sold": 88,
    "totalSeats": 1409,
    "venues": 9,
    "cities": 6,
    "fastfilling": 0,
    "housefull": 0,
    "occupancy": 6.25
  },
  "Vrusshabha [2D | Malayalam]": {
    "shows": 34,
    "gross": 36732.0,
    "sold": 212,
    "totalSeats": 6982,
    "venues": 26,
    "cities": 11,
    "fastfilling": 0,
    "housefull": 0,
    "occupancy": 3.04
  },
  "Haal (Malayalam) [2D | Malayalam]": {
    "shows": 35,
    "gross": 73291.8,
    "sold": 418,
    "totalSeats": 5876,
    "venues": 20,
    "cities": 10,
    "fastfilling": 0,
    "housefull": 0,
    "occupancy": 7.11
  },
  "Zootopia 2 [3D | English]": {
    "shows": 12,
    "gross": 318025.0,
    "sold": 959,
    "totalSeats": 1754,
    "venues": 7,
    "cities": 4,
    "fastfilling": 6,
    "housefull": 0,
    "occupancy": 54.68
  },
  "Anaconda [2D | Tamil]": {
    "shows": 2,
    "gross": 3075.2,
    "sold": 28,
    "totalSeats": 247,
    "venues": 2,
    "cities": 2,
    "fastfilling": 0,
    "housefull": 0,
    "occupancy": 11.34
  },
  "Vrusshabha [2D | Hindi]": {
    "shows": 16,
    "gross": 18668.0,
    "sold": 119,
    "totalSeats": 2618,
    "venues": 10,
    "cities": 10,
    "fastfilling": 0,
    "housefull": 1,
    "occupancy": 4.55
  },
  "Kali Maati [2D | Marathi]": {
    "shows": 1,
    "gross": 0.0,
    "sold": 0,
    "totalSeats": 112,
    "venues": 1,
    "cities": 1,
    "fastfilling": 0,
    "housefull": 0,
    "occupancy": 0.0
  },
  "Prit Janmo Janmi Bhulache Nahi [2D | Gujarati]": {
    "shows": 1,
    "gross": 0.0,
    "sold": 0,
    "totalSeats": 296,
    "venues": 1,
    "cities": 1,
    "fastfilling": 0,
    "housefull": 0,
    "occupancy": 0.0
  },
  "Anaconda [2D | English]": {
    "shows": 51,
    "gross": 129122.0,
    "sold": 524,
    "totalSeats": 9398,
    "venues": 43,
    "cities": 11,
    "fastfilling": 0,
    "housefull": 0,
    "occupancy": 5.58
  },
  "Eesha [2D | Telugu]": {
    "shows": 28,
    "gross": 137930.0,
    "sold": 1102,
    "totalSeats": 7439,
    "venues": 15,
    "cities": 7,
    "fastfilling": 2,
    "housefull": 0,
    "occupancy": 14.81
  },
  "Paruthi [2D | Tamil]": {
    "shows": 3,
    "gross": 0.0,
    "sold": 0,
    "totalSeats": 1317,
    "venues": 1,
    "cities": 1,
    "fastfilling": 0,
    "housefull": 0,
    "occupancy": 0.0
  },
  "Dhandoraa [2D | Telugu]": {
    "shows": 13,
    "gross": 33235.0,
    "sold": 238,
    "totalSeats": 2843,
    "venues": 7,
    "cities": 5,
    "fastfilling": 0,
    "housefull": 0,
    "occupancy": 8.37
  },
  "Anaconda [2D | Telugu]": {
    "shows": 4,
    "gross": 67310.0,
    "sold": 534,
    "totalSeats": 1132,
    "venues": 3,
    "cities": 3,
    "fastfilling": 1,
    "housefull": 0,
    "occupancy": 47.17
  },
  "Akhanda 2: Thaandavam [3D | Telugu]": {
    "shows": 3,
    "gross": 7950.0,
    "sold": 53,
    "totalSeats": 884,
    "venues": 2,
    "cities": 2,
    "fastfilling": 0,
    "housefull": 0,
    "occupancy": 6.0
  },
  "Mark [2D | Kannada]": {
    "shows": 167,
    "gross": 2025925.0,
    "sold": 9018,
    "totalSeats": 66466,
    "venues": 72,
    "cities": 3,
    "fastfilling": 11,
    "housefull": 0,
    "occupancy": 13.57
  },
  "45 [2D | Kannada]": {
    "shows": 154,
    "gross": 1460000.0,
    "sold": 7200,
    "totalSeats": 68383,
    "venues": 70,
    "cities": 3,
    "fastfilling": 13,
    "housefull": 0,
    "occupancy": 10.53
  },
  "The Devil [2D | Kannada]": {
    "shows": 21,
    "gross": 115070.0,
    "sold": 635,
    "totalSeats": 6090,
    "venues": 16,
    "cities": 2,
    "fastfilling": 0,
    "housefull": 0,
    "occupancy": 10.43
  },
  "Avatar: Fire and Ash [3D | Kannada]": {
    "shows": 2,
    "gross": 4600.0,
    "sold": 23,
    "totalSeats": 412,
    "venues": 1,
    "cities": 1,
    "fastfilling": 0,
    "housefull": 0,
    "occupancy": 5.58
  },
  "Kantara: A Legend Chapter-1 [2D | Kannada]": {
    "shows": 3,
    "gross": 1800.0,
    "sold": 15,
    "totalSeats": 2277,
    "venues": 1,
    "cities": 1,
    "fastfilling": 0,
    "housefull": 0,
    "occupancy": 0.66
  },
  "Vrusshabha [2D | Kannada]": {
    "shows": 5,
    "gross": 50340.0,
    "sold": 378,
    "totalSeats": 3888,
    "venues": 2,
    "cities": 2,
    "fastfilling": 0,
    "housefull": 0,
    "occupancy": 9.72
  },
  "Eko [2D | Malayalam]": {
    "shows": 3,
    "gross": 18045.0,
    "sold": 77,
    "totalSeats": 318,
    "venues": 3,
    "cities": 2,
    "fastfilling": 0,
    "housefull": 0,
    "occupancy": 24.21
  },
  "Kalamkaval [2D | Malayalam]": {
    "shows": 24,
    "gross": 49168.4,
    "sold": 264,
    "totalSeats": 4193,
    "venues": 18,
    "cities": 6,
    "fastfilling": 0,
    "housefull": 0,
    "occupancy": 6.3
  },
  "Avatar: Fire and Ash [3D | Malayalam]": {
    "shows": 3,
    "gross": 10130.0,
    "sold": 54,
    "totalSeats": 676,
    "venues": 2,
    "cities": 2,
    "fastfilling": 0,
    "housefull": 0,
    "occupancy": 7.99
  },
  "Gurram Paapi Reddy [2D | Telugu]": {
    "shows": 1,
    "gross": 1386.0,
    "sold": 14,
    "totalSeats": 233,
    "venues": 1,
    "cities": 1,
    "fastfilling": 0,
    "housefull": 0,
    "occupancy": 6.01
  },
  "Vrusshabha [2D | Telugu]": {
    "shows": 4,
    "gross": 24540.0,
    "sold": 183,
    "totalSeats": 1539,
    "venues": 2,
    "cities": 2,
    "fastfilling": 0,
    "housefull": 0,
    "occupancy": 11.89
  },
  "Avatar: Fire and Ash [IMAX 3D | English]": {
    "shows": 17,
    "gross": 1810899.0,
    "sold": 2270,
    "totalSeats": 4951,
    "venues": 7,
    "cities": 2,
    "fastfilling": 8,
    "housefull": 0,
    "occupancy": 45.85
  },
  "Anaconda [4DX | English]": {
    "shows": 8,
    "gross": 83030.0,
    "sold": 181,
    "totalSeats": 788,
    "venues": 7,
    "cities": 3,
    "fastfilling": 0,
    "housefull": 0,
    "occupancy": 22.97
  },
  "Zootopia 2 [2D | English]": {
    "shows": 4,
    "gross": 76691.0,
    "sold": 280,
    "totalSeats": 634,
    "venues": 3,
    "cities": 2,
    "fastfilling": 1,
    "housefull": 0,
    "occupancy": 44.16
  },
  "Avatar: Fire and Ash [4DX 3D | English]": {
    "shows": 17,
    "gross": 819890.0,
    "sold": 1252,
    "totalSeats": 1684,
    "venues": 8,
    "cities": 4,
    "fastfilling": 12,
    "housefull": 1,
    "occupancy": 74.35
  },
  "Vaama: Ladai Sanmanachi [2D | Marathi]": {
    "shows": 3,
    "gross": 0.0,
    "sold": 0,
    "totalSeats": 750,
    "venues": 1,
    "cities": 1,
    "fastfilling": 0,
    "housefull": 0,
    "occupancy": 0.0
  },
  "Avatar: Fire and Ash [4DX 3D | Hindi]": {
    "shows": 4,
    "gross": 117490.0,
    "sold": 263,
    "totalSeats": 412,
    "venues": 2,
    "cities": 2,
    "fastfilling": 3,
    "housefull": 0,
    "occupancy": 63.83
  },
  "Anaconda [MX4D | Hindi]": {
    "shows": 1,
    "gross": 14240.0,
    "sold": 38,
    "totalSeats": 100,
    "venues": 1,
    "cities": 1,
    "fastfilling": 0,
    "housefull": 0,
    "occupancy": 38.0
  },
  "Avatar: Fire and Ash [MX4D 3D | English]": {
    "shows": 1,
    "gross": 28800.0,
    "sold": 59,
    "totalSeats": 100,
    "venues": 1,
    "cities": 1,
    "fastfilling": 1,
    "housefull": 0,
    "occupancy": 59.0
  },
  "Lawho Gouranger Naam Rey [2D | Bengali]": {
    "shows": 9,
    "gross": 28510.0,
    "sold": 213,
    "totalSeats": 2027,
    "venues": 9,
    "cities": 6,
    "fastfilling": 0,
    "housefull": 0,
    "occupancy": 10.51
  },
  "Roi Roi Binale [2D | Assamese]": {
    "shows": 2,
    "gross": 7750.0,
    "sold": 55,
    "totalSeats": 360,
    "venues": 1,
    "cities": 1,
    "fastfilling": 0,
    "housefull": 0,
    "occupancy": 15.28
  },
  "Mission Santa: Yoyo to the Rescue [2D | English]": {
    "shows": 7,
    "gross": 63810.0,
    "sold": 212,
    "totalSeats": 991,
    "venues": 7,
    "cities": 3,
    "fastfilling": 2,
    "housefull": 0,
    "occupancy": 21.39
  },
  "Acharya Sri Shankara [2D | Kannada]": {
    "shows": 1,
    "gross": 11920.0,
    "sold": 80,
    "totalSeats": 195,
    "venues": 1,
    "cities": 1,
    "fastfilling": 0,
    "housefull": 0,
    "occupancy": 41.03
  },
  "Padayappa [2D | Tamil]": {
    "shows": 2,
    "gross": 4423.12,
    "sold": 37,
    "totalSeats": 938,
    "venues": 2,
    "cities": 2,
    "fastfilling": 0,
    "housefull": 0,
    "occupancy": 3.94
  },
  "Krack (Telugu) [2D | Telugu]": {
    "shows": 2,
    "gross": 0.0,
    "sold": 0,
    "totalSeats": 566,
    "venues": 1,
    "cities": 1,
    "fastfilling": 0,
    "housefull": 0,
    "occupancy": 0.0
  },
  "Zootopia 2 [2D | Hindi]": {
    "shows": 2,
    "gross": 3480.0,
    "sold": 20,
    "totalSeats": 355,
    "venues": 1,
    "cities": 1,
    "fastfilling": 0,
    "housefull": 0,
    "occupancy": 5.63
  },
  "Bad Girlz (Kaani Chala Manchollu) [2D | Telugu]": {
    "shows": 2,
    "gross": 447.0,
    "sold": 5,
    "totalSeats": 466,
    "venues": 1,
    "cities": 1,
    "fastfilling": 0,
    "housefull": 0,
    "occupancy": 1.07
  },
  "Anaconda [4DX | Hindi]": {
    "shows": 1,
    "gross": 12920.0,
    "sold": 34,
    "totalSeats": 88,
    "venues": 1,
    "cities": 1,
    "fastfilling": 0,
    "housefull": 0,
    "occupancy": 38.64
  },
  "Avatar: Fire and Ash [2D | English]": {
    "shows": 3,
    "gross": 13576.7,
    "sold": 25,
    "totalSeats": 357,
    "venues": 3,
    "cities": 3,
    "fastfilling": 1,
    "housefull": 0,
    "occupancy": 7.0
  },
  "Avatar: Fire and Ash [2D | Tamil]": {
    "shows": 1,
    "gross": 1110.0,
    "sold": 8,
    "totalSeats": 841,
    "venues": 1,
    "cities": 1,
    "fastfilling": 0,
    "housefull": 0,
    "occupancy": 0.95
  },
  "Savitri Kalyugatali [2D | Marathi]": {
    "shows": 1,
    "gross": 0.0,
    "sold": 0,
    "totalSeats": 132,
    "venues": 1,
    "cities": 1,
    "fastfilling": 0,
    "housefull": 0,
    "occupancy": 0.0
  },
  "Avatar: Fire and Ash [MX4D 3D | Hindi]": {
    "shows": 1,
    "gross": 28600.0,
    "sold": 59,
    "totalSeats": 100,
    "venues": 1,
    "cities": 1,
    "fastfilling": 1,
    "housefull": 0,
    "occupancy": 59.0
  },
  "Khadaan [2D | Bengali]": {
    "shows": 1,
    "gross": 70.0,
    "sold": 1,
    "totalSeats": 60,
    "venues": 1,
    "cities": 1,
    "fastfilling": 0,
    "housefull": 0,
    "occupancy": 1.67
  },
  "Jeev [2D | Gujarati]": {
    "shows": 3,
    "gross": 10700.0,
    "sold": 103,
    "totalSeats": 614,
    "venues": 2,
    "cities": 1,
    "fastfilling": 0,
    "housefull": 0,
    "occupancy": 16.78
  },
  "Kombuseevi [2D | Tamil]": {
    "shows": 1,
    "gross": 4940.0,
    "sold": 38,
    "totalSeats": 521,
    "venues": 1,
    "cities": 1,
    "fastfilling": 0,
    "housefull": 0,
    "occupancy": 7.29
  },
  "Rappa Roy & Full Stop Dot Com [2D | Bengali]": {
    "shows": 1,
    "gross": 0.0,
    "sold": 0,
    "totalSeats": 381,
    "venues": 1,
    "cities": 1,
    "fastfilling": 0,
    "housefull": 0,
    "occupancy": 0.0
  }
}